channel_exporter/__init__.py
channel_exporter/i channel_exporter.py
channel_exporter-1.1.2.dist-info/licenses/LICENSE
channel_exporter-1.1.2.dist-info/METADATA
channel_exporter-1.1.2.dist-info/WHEEL
channel_exporter-1.1.2.dist-info/top_level.txt
channel_exporter-1.1.2.dist-info/RECORD
