Metadata-Version: 2.4
Name: channel-exporter
Version: 1.1.2
Summary: 用于 Python 应用的 Prometheus 指标监控库，支持 Flask、Requests 和消息队列消费 者的监控指标自动收集。
Author: Unnamed great master
Author-email: <gqylpy@outlook.com>
License: MIT
Project-URL: Source, https://github.com/2018-11-27/channel-exporter
Classifier: Development Status :: 3 - Alpha
Classifier: Intended Audience :: Developers
Classifier: License :: OSI Approved :: MIT License
Classifier: Natural Language :: Chinese (Simplified)
Classifier: Natural Language :: English
Classifier: Operating System :: OS Independent
Classifier: Topic :: Software Development :: Libraries :: Python Modules
Classifier: Topic :: Artistic Software
Classifier: Topic :: Scientific/Engineering :: Mathematics
Classifier: Programming Language :: Python :: 2.7
Classifier: Programming Language :: Python :: 3
Classifier: Programming Language :: Python :: 3.6
Classifier: Programming Language :: Python :: 3.7
Classifier: Programming Language :: Python :: 3.8
Classifier: Programming Language :: Python :: 3.9
Classifier: Programming Language :: Python :: 3.10
Classifier: Programming Language :: Python :: 3.11
Classifier: Programming Language :: Python :: 3.12
Classifier: Programming Language :: Python :: 3.13
Requires-Python: >=2.7
License-File: LICENSE
Requires-Dist: prometheus_client
Provides-Extra: flask
Requires-Dist: Flask>=0.10; extra == "flask"
Provides-Extra: requests
Requires-Dist: requests>=2.19; extra == "requests"
Provides-Extra: ctec-consumer
Requires-Dist: ctec-consumer==0.3.7; extra == "ctec-consumer"
Provides-Extra: gevent
Requires-Dist: gevent>=1.2.2; extra == "gevent"
Dynamic: author
Dynamic: author-email
Dynamic: classifier
Dynamic: description
Dynamic: description-content-type
Dynamic: license
Dynamic: license-file
Dynamic: project-url
Dynamic: provides-extra
Dynamic: requires-dist
Dynamic: requires-python
Dynamic: summary
